src/__init__.py
src/constants.py
src/main.py
gendia-1.6.2.dist-info/LICENSE
gendia-1.6.2.dist-info/METADATA
gendia-1.6.2.dist-info/WHEEL
gendia-1.6.2.dist-info/entry_points.txt
gendia-1.6.2.dist-info/top_level.txt
gendia-1.6.2.dist-info/RECORD
