Metadata-Version: 2.1
Name: gendia
Version: 1.6.2
Summary: A Python CLI to generate a tree structured diagram for any directory
Home-page: https://github.com/Silicon27/gendia
Author: Silicon27
Author-email: yangsilicon@gmail.com
Classifier: Programming Language :: Python :: 3
Classifier: License :: OSI Approved :: MIT License
Classifier: Operating System :: OS Independent
Requires-Python: >=3.6
License-File: LICENSE
